demos/__init__.py
demos/pydantic_demo.py
demos/model_depends/__init__.py
demos/model_depends/queue_demo.py
laner/__init__.py
laner/pydantic.py
laner/model_depends/__init__.py
laner/model_depends/queue.py
laner-1.3.4.dist-info/LICENSE
laner-1.3.4.dist-info/METADATA
laner-1.3.4.dist-info/WHEEL
laner-1.3.4.dist-info/top_level.txt
laner-1.3.4.dist-info/RECORD
