Metadata-Version: 2.1
Name: laner
Version: 1.3.4
Summary: 一个非常实用的包
Author: lane
Author-email: changlei-886@163.com
Classifier: Programming Language :: Python :: 3
Classifier: License :: OSI Approved :: MIT License
Classifier: Operating System :: OS Independent
Requires-Python: >=3.9.0
License-File: LICENSE
Requires-Dist: pydantic
